varats-13.0.5-py3.11-nspkg.pth
varats/containers/__init__.py
varats/containers/containers.py
varats/data/__init__.py
varats/data/cache_helper.py
varats/data/data_manager.py
varats/data/discover_reports.py
varats/data/filtertree_data.py
varats/data/metrics.py
varats/data/databases/__init__.py
varats/data/databases/blame_diff_library_interaction_database.py
varats/data/databases/blame_diff_metrics_database.py
varats/data/databases/blame_interaction_database.py
varats/data/databases/blame_interaction_degree_database.py
varats/data/databases/blame_library_interactions_database.py
varats/data/databases/blame_verifier_report_database.py
varats/data/databases/commit_interaction_database.py
varats/data/databases/evaluationdatabase.py
varats/data/databases/feature_perf_precision_database.py
varats/data/databases/file_status_database.py
varats/data/databases/szz_quality_metrics_database.py
varats/data/reports/__init__.py
varats/data/reports/blame_annotations.py
varats/data/reports/blame_interaction_graph.py
varats/data/reports/blame_report.py
varats/data/reports/blame_verifier_report.py
varats/data/reports/commit_report.py
varats/data/reports/compiled_binary_report.py
varats/data/reports/empty_report.py
varats/data/reports/env_trace_report.py
varats/data/reports/feature_analysis_report.py
varats/data/reports/feature_instrumentation_points_report.py
varats/data/reports/feature_tracing_stats_report.py
varats/data/reports/globals_report.py
varats/data/reports/instrumentation_verifier_report.py
varats/data/reports/perf_profile_report.py
varats/data/reports/performance_influence_trace_report.py
varats/data/reports/region_verification_report.py
varats/data/reports/szz_report.py
varats/data/reports/taint_report.py
varats/experiments/__init__.py
varats/experiments/discover_experiments.py
varats/experiments/base/__init__.py
varats/experiments/base/just_compile.py
varats/experiments/base/time_workloads.py
varats/experiments/phasar/__init__.py
varats-13.0.5.dist-info/METADATA
varats-13.0.5.dist-info/WHEEL
varats-13.0.5.dist-info/entry_points.txt
varats-13.0.5.dist-info/namespace_packages.txt
varats-13.0.5.dist-info/top_level.txt
varats-13.0.5.dist-info/RECORD
