Metadata-Version: 2.1
Name: varats
Version: 13.0.5
Home-page: https://github.com/se-sic/vara-tool-suite
Author: Florian Sattler
Author-email: sattlerf@cs.uni-saarland.de
License: BSD 2-Clause
Requires-Python: >=3.9
Requires-Dist: benchbuild>=6.8
Requires-Dist: click>=8.1.3
Requires-Dist: distro>=1.5.0
Requires-Dist: graphviz>=0.14.2
Requires-Dist: Jinja2>=3.1.2
Requires-Dist: kaleido>=0.2.1
Requires-Dist: matplotlib>=3.8.2
Requires-Dist: networkx>=3.0
Requires-Dist: numpy>=1.24.2
Requires-Dist: packaging>=20.1
Requires-Dist: pandas>=1.5.3
Requires-Dist: plotly>=5.13.1
Requires-Dist: plumbum>=1.6
Requires-Dist: pygit2<1.14.0,>=1.10
Requires-Dist: PyGithub>=1.47
Requires-Dist: pygraphviz>=1.7
Requires-Dist: pygtrie>=2.3
Requires-Dist: pylatex>=1.4.1
Requires-Dist: PyQt5>=5.10.0
Requires-Dist: PyQt5-stubs>=5.10.0
Requires-Dist: PyYAML>=6.0
Requires-Dist: rich>=12.6
Requires-Dist: scikit-learn>=1.2.2
Requires-Dist: seaborn>=0.13.0
Requires-Dist: tabulate>=0.9
Requires-Dist: varats-core>=13.0.5
Requires-Dist: wllvm>=1.3.1
Requires-Dist: cliffs-delta>=1.0.0
